[
  {
    "store_id": "store-001",
    "stage": "prior",
    "metadata.schema_version": "v1",
    "metadata.store_type": "Thrift",
    "baseline.value": 2.8,
    "baseline.yield": 3.4,
    "affluence.income": 0.5,
    "affluence.high_income": 0.3,
    "affluence.renter": -0.2,
    "adjacency.value": 0.0,
    "adjacency.yield": 0.0,
    "observations.lambda_weight": 0.5,
    "model.parameters_hash": "bf54c6d21d7a0148d3ecba23c07bd9e5",
    "model.posterior_overrides_present": false,
    "scores.value": 3.6,
    "scores.yield": 3.2,
    "scores.composite": 3.4
  },
  {
    "store_id": "store-002",
    "stage": "posterior",
    "metadata.schema_version": "v1",
    "baseline.theta_prediction": 3.1,
    "baseline.value_prediction": 3.2,
    "affluence.MedianIncome": 55000.0,
    "adjacency.theta": 0.05,
    "adjacency.value": -0.02,
    "observations.visits": 120.0,
    "observations.dwell_total": 4560.0,
    "observations.items_total": 980.0,
    "observations.value_mean": 3.35,
    "observations.theta_observed": 3.0,
    "observations.method": "GLM",
    "observations.theta_uncertainty": 0.2,
    "observations.value_uncertainty": 0.15,
    "model.parameters_hash": "9d41cb6dff41083a7c8c27da6c4f90cb",
    "model.yield_family": "gaussian",
    "model.min_samples_glm": 30,
    "model.knn_k": 5,
    "model.knn_smoothing_factor": 0.5,
    "scores.theta_final": 3.05,
    "scores.yield_final": 3.4,
    "scores.value_final": 3.3,
    "scores.credibility": 0.8,
    "scores.ecdf_quantile": 0.65
  },
  {
    "store_id": "store-003",
    "stage": "blend",
    "metadata.schema_version": "v1",
    "observations.omega": 0.4,
    "model.lambda_weight": 0.5,
    "scores.value_prior": 3.4,
    "scores.value_posterior": 3.6,
    "scores.value_final": 3.5,
    "scores.yield_prior": 3.1,
    "scores.yield_posterior": 3.45,
    "scores.yield_final": 3.3,
    "scores.composite_prior": 3.25,
    "scores.composite_final": 3.4
  }
]
